mastercard_mcaid_analytics-1.0.2.dist-info/DESCRIPTION.rst
mastercard_mcaid_analytics-1.0.2.dist-info/METADATA
mastercard_mcaid_analytics-1.0.2.dist-info/RECORD
mastercard_mcaid_analytics-1.0.2.dist-info/WHEEL
mastercard_mcaid_analytics-1.0.2.dist-info/metadata.json
mastercard_mcaid_analytics-1.0.2.dist-info/top_level.txt
mastercardmcaidanalytics/__init__.py
mastercardmcaidanalytics/cards.py
mastercardmcaidanalytics/devices.py
mastercardmcaidanalytics/merchants.py
mastercardmcaidanalytics/products.py
mastercardmcaidanalytics/programs.py
mastercardmcaidanalytics/resourceconfig.py
mastercardmcaidanalytics/transactions.py
